setup.py
meteorpi_fdb/__init__.py
meteorpi_fdb/exporter.py
meteorpi_fdb/generators.py
meteorpi_fdb/sql_builder.py
meteorpi_fdb.egg-info/PKG-INFO
meteorpi_fdb.egg-info/SOURCES.txt
meteorpi_fdb.egg-info/dependency_links.txt
meteorpi_fdb.egg-info/not-zip-safe
meteorpi_fdb.egg-info/requires.txt
meteorpi_fdb.egg-info/top_level.txt