Metadata-Version: 1.1
Name: meteorpi-fdb
Version: 0.1.5
Summary: Data access layer, uses FireBird to persist and retrieve MeteorPi classes
Home-page: https://github.com/camsci/meteor-pi/
Author: Tom Oinn
Author-email: tomoinn@crypticsquid.com
License: GPL
Platform: UNKNOWN
Classifier: Programming Language :: Python :: 2.7
